collectlicense/__init__.py
collectlicense/__main__.py
collectlicense/config.yml
collectlicense/logconf.yml
collectlicense/version.py
collectlicense/app/__init__.py
collectlicense/app/app.py
collectlicense/app/common.py
collectlicense-0.2.0.dist-info/LICENSE
collectlicense-0.2.0.dist-info/METADATA
collectlicense-0.2.0.dist-info/WHEEL
collectlicense-0.2.0.dist-info/top_level.txt
collectlicense-0.2.0.dist-info/RECORD
