Metadata-Version: 2.1
Name: collectlicense
Version: 0.2.0
Summary: collect-license: Collect license files for packages installed with pip.
Home-page: https://github.com/hamacom2004jp/collect-license
Download-URL: https://github.com/hamacom2004jp/collect-license
Author: hamacom2004jp
Author-email: hamacom2004jp@gmail.com
Maintainer: hamacom2004jp
Maintainer-email: hamacom2004jp@gmail.com
License: MIT
Keywords: LICENSE.txt LICENSE Collect
Classifier: Development Status :: 4 - Beta
Classifier: Intended Audience :: Developers
Classifier: Intended Audience :: Information Technology
Classifier: Intended Audience :: System Administrators
Classifier: License :: OSI Approved :: MIT License
Classifier: Natural Language :: Japanese
Classifier: Programming Language :: Python
Classifier: Topic :: Utilities
License-File: LICENSE
Requires-Dist: PyYAML>=6.0.1
Requires-Dist: pip-licenses>=4.3.3
